LICENSE
README.md
setup.py
src/cvhub.egg-info/PKG-INFO
src/cvhub.egg-info/SOURCES.txt
src/cvhub.egg-info/dependency_links.txt
src/cvhub.egg-info/top_level.txt
src/mgmatting/__init__.py
src/mgmatting/net_engine.py
src/mgmatting/dataloader/__init__.py
src/mgmatting/dataloader/data_generator.py
src/mgmatting/dataloader/image_file.py
src/mgmatting/dataloader/prefetcher.py
src/mgmatting/networks/__init__.py
src/mgmatting/networks/generators.py
src/mgmatting/networks/ops.py
src/mgmatting/networks/decoders/__init__.py
src/mgmatting/networks/decoders/res_shortcut_dec.py
src/mgmatting/networks/decoders/resnet_dec.py
src/mgmatting/networks/encoders/__init__.py
src/mgmatting/networks/encoders/res_shortcut_enc.py
src/mgmatting/networks/encoders/resnet_enc.py
src/mgmatting/utils/__init__.py
src/mgmatting/utils/config.py
src/mgmatting/utils/copy_data.py
src/mgmatting/utils/evaluate.py
src/mgmatting/utils/logger.py
src/mgmatting/utils/util.py
src/u2net/__init__.py
src/u2net/data_loader.py
src/u2net/net_engine.py
src/u2net/model/__init__.py
src/u2net/model/u2net.py
src/u2net/model/u2net_refactor.py